LICENSE.txt
MANIFEST.in
ez_setup.py
remove_pyreadline.py
setup.py
src/common_crypto.py
src/common_crypto_test.py
src/common_util.py
src/common_util_test.py
src/ebq.py
src/ebq_crypto.py
src/ebq_crypto_test.py
src/encrypted_bigquery_client.py
src/encrypted_bigquery_client_test.py
src/load_lib.py
src/load_lib_test.py
src/number.py
src/number_test.py
src/paillier.py
src/paillier_test.py
src/query_interpreter.py
src/query_interpreter_test.py
src/query_lib.py
src/query_lib_test.py
src/query_parser.py
src/query_parser_test.py
src/run_all_tests.py
src/show_lib.py
src/show_lib_test.py
src/test_util.py
src/encrypted_bigquery.egg-info/PKG-INFO
src/encrypted_bigquery.egg-info/SOURCES.txt
src/encrypted_bigquery.egg-info/dependency_links.txt
src/encrypted_bigquery.egg-info/entry_points.txt
src/encrypted_bigquery.egg-info/requires.txt
src/encrypted_bigquery.egg-info/top_level.txt