Metadata-Version: 1.1
Name: encrypted-bigquery
Version: 1.46
Summary: Encrypted BigQuery command-line tool
Home-page: http://code.google.com/p/encrypted-bigquery-client/
Author: Google Inc.
Author-email: ebq-team@google.com
License: Apache 2.0
Keywords: google encrypted bigquery library
Platform: UNKNOWN
Classifier: Development Status :: 4 - Beta
Classifier: Environment :: Console
Classifier: Intended Audience :: Developers
Classifier: Intended Audience :: End Users/Desktop
Classifier: License :: OSI Approved :: Apache Software License
Classifier: Operating System :: MacOS :: MacOS X
Classifier: Operating System :: Microsoft :: Windows
Classifier: Operating System :: POSIX :: Linux
Classifier: Programming Language :: Python :: 2.7
Classifier: Topic :: Database :: Front-Ends
Classifier: Topic :: Software Development :: Libraries
Classifier: Topic :: Software Development :: Libraries :: Python Modules
Provides: encrypted_bigquery (1.46)
